opipy_pm/__init__.py
opipy_pm/Models/__init__.py
opipy_pm/Models/ml/__init__.py
opipy_pm/Models/nn/__init__.py
opipy_pm/Models/nn/TF/Classifier.py
opipy_pm/Models/nn/TF/__init__.py
opipy_pm/Models/nn/Torch/Classifier.py
opipy_pm/Models/nn/Torch/__init__.py
opipy_pm/Models/nn/Torch/functional.py
opipy_pm/utils/__init__.py
opipy_pm/utils/functional.py
opipy_pm-0.1.3.dist-info/LICENSE
opipy_pm-0.1.3.dist-info/METADATA
opipy_pm-0.1.3.dist-info/WHEEL
opipy_pm-0.1.3.dist-info/top_level.txt
opipy_pm-0.1.3.dist-info/RECORD
