Metadata-Version: 2.1
Name: opipy_pm
Version: 0.1.3
Summary: OPI Solutions Python package for Predictive Maintenance
Author-email: "Daniel E. Diaz Almeida" <daniel.diazalmeida@opi-solutions.com>
License: Apache License
Project-URL: Homepage, https://github.com/OPISolutions/opipy_pm
Project-URL: Issues, https://github.com/OPISolutions/opipy_pm/issues
Keywords: opipy,predictive maintenance,machine learning,artificial intelligence
Classifier: Development Status :: 2 - Pre-Alpha
Classifier: Intended Audience :: Developers
Classifier: Intended Audience :: Education
Classifier: Intended Audience :: Science/Research
Classifier: Topic :: Scientific/Engineering
Classifier: Topic :: Scientific/Engineering :: Mathematics
Classifier: Topic :: Scientific/Engineering :: Artificial Intelligence
Classifier: Topic :: Software Development
Classifier: Topic :: Software Development :: Libraries
Classifier: Topic :: Software Development :: Libraries :: Python Modules
Classifier: Programming Language :: Python :: 3.8
Classifier: Programming Language :: Python :: 3.9
Classifier: Programming Language :: Python :: 3.10
Classifier: Programming Language :: Python :: 3.11
Classifier: Programming Language :: Python :: 3.12
Classifier: License :: OSI Approved :: Apache Software License
Classifier: Operating System :: OS Independent
Requires-Python: >=3.8
License-File: LICENSE
Requires-Dist: numpy
Requires-Dist: pandas
Requires-Dist: matplotlib
Requires-Dist: seaborn
Requires-Dist: shap
Requires-Dist: scikit-learn
Requires-Dist: tensorflow>=2.16.1
Requires-Dist: altair>=5.4.0
Requires-Dist: torch>=2.3.1
Requires-Dist: xgboost>=2.1.0
Requires-Dist: torchmetrics>=1.4.0
